atomdateparser/__init__.py
atomdateparser/handlers.py
atomdateparser/parser.py
atomdateparser/stringutils.py
atomdateparser/test/__init__.py
atomdateparser/test/test_parser.py
atomdateparser-0.0.2.dist-info/LICENSE
atomdateparser-0.0.2.dist-info/METADATA
atomdateparser-0.0.2.dist-info/WHEEL
atomdateparser-0.0.2.dist-info/top_level.txt
atomdateparser-0.0.2.dist-info/RECORD
