Metadata-Version: 2.1
Name: atomdateparser
Version: 0.0.2
Summary: Parse eventDates for AtoM CSVs
Home-page: https://github.com/NationalCentreTruthReconciliation/AtoM-Event-Date-Parser
Author: Daniel Lovegrove
Author-email: d.lovegrove11@gmail.com
License: MIT
Requires-Python: >=3.6
License-File: LICENSE
Requires-Dist: dateparser (>=1.0.0)
Provides-Extra: dev
Requires-Dist: pytest ; extra == 'dev'
